ccx_messaging/__init__.py
ccx_messaging/command_line.py
ccx_messaging/error.py
ccx_messaging/ingress.py
ccx_messaging/internal_pipeline.py
ccx_messaging/monitored_broker.py
ccx_messaging/schemas.py
ccx_messaging/consumers/__init__.py
ccx_messaging/consumers/decoded_ingress_consumer.py
ccx_messaging/consumers/idp_kafka_consumer.py
ccx_messaging/consumers/kafka_consumer.py
ccx_messaging/consumers/rules_results_consumer.py
ccx_messaging/consumers/synced_archive_consumer.py
ccx_messaging/downloaders/__init__.py
ccx_messaging/downloaders/http_downloader.py
ccx_messaging/downloaders/s3_downloader.py
ccx_messaging/engines/__init__.py
ccx_messaging/engines/multiplexor_engine.py
ccx_messaging/engines/ocp_engine.py
ccx_messaging/engines/s3_upload_engine.py
ccx_messaging/engines/sha_extractor_engine.py
ccx_messaging/publishers/__init__.py
ccx_messaging/publishers/dvo_metrics_publisher.py
ccx_messaging/publishers/idp_rule_processing_publisher.py
ccx_messaging/publishers/kafka_publisher.py
ccx_messaging/publishers/multiplexor_kafka_publisher.py
ccx_messaging/publishers/rule_processing_publisher.py
ccx_messaging/publishers/synced_archive_publisher.py
ccx_messaging/publishers/workloads_info_publisher.py
ccx_messaging/utils/__init__.py
ccx_messaging/utils/clowder.py
ccx_messaging/utils/kafka_config.py
ccx_messaging/utils/logging.py
ccx_messaging/utils/s3_uploader.py
ccx_messaging/utils/sentry.py
ccx_messaging/utils/sliced_template.py
ccx_messaging/watchers/__init__.py
ccx_messaging/watchers/cluster_id_watcher.py
ccx_messaging/watchers/consumer_watcher.py
ccx_messaging/watchers/payload_tracker_watcher.py
ccx_messaging/watchers/stats_watcher.py
ccx_messaging-4.3.6.dist-info/licenses/LICENSE
ccx_messaging-4.3.6.dist-info/METADATA
ccx_messaging-4.3.6.dist-info/WHEEL
ccx_messaging-4.3.6.dist-info/entry_points.txt
ccx_messaging-4.3.6.dist-info/top_level.txt
ccx_messaging-4.3.6.dist-info/RECORD
