Metadata-Version: 2.4
Name: ccx-messaging
Version: 4.3.6
Author-email: CCX Processing Team <ccx-core-processing-team@redhat.com>
License: Apache-2.0
Project-URL: Homepage, https://github.com/RedHatInsights/insights-ccx-messaging
Classifier: Intended Audience :: Developers
Classifier: Natural Language :: English
Classifier: License :: OSI Approved :: Apache Software License
Classifier: Programming Language :: Python
Classifier: Programming Language :: Python :: 3
Classifier: Programming Language :: Python :: 3.8
Classifier: Programming Language :: Python :: 3.9
Classifier: Programming Language :: Python :: 3.10
Classifier: Programming Language :: Python :: 3.11
Classifier: Programming Language :: Python :: 3.12
Requires-Python: >=3.8
License-File: LICENSE
Requires-Dist: app-common-python>=0.2.3
Requires-Dist: boto3<1.42.26,>=1.34.1
Requires-Dist: confluent-kafka>=2.0.0
Requires-Dist: insights-core>=3.1.2
Requires-Dist: insights-core-messaging>=1.2.15
Requires-Dist: jsonschema>=4.0.0
Requires-Dist: prometheus-client>=0.16.0
Requires-Dist: python-json-logger<5,>=2.0.7
Requires-Dist: PyYAML>=6.0
Requires-Dist: requests>=2.31.0
Requires-Dist: sentry-sdk>=1.37.1
Requires-Dist: watchtower>=3.0.0
Provides-Extra: test
Requires-Dist: pytest; extra == "test"
Requires-Dist: pytest-cov; extra == "test"
Requires-Dist: freezegun; extra == "test"
Provides-Extra: dev
Requires-Dist: coverage; extra == "dev"
Requires-Dist: pycco; extra == "dev"
Requires-Dist: ruff; extra == "dev"
Dynamic: license-file
